pyqn/__init__.py
pyqn/atom_unit.py
pyqn/base_unit.py
pyqn/dimensions.py
pyqn/list_base_units.py
pyqn/qn_array.py
pyqn/quantity.py
pyqn/si.py
pyqn/symbol.py
pyqn/units.py
pyqn-1.4.1.dist-info/LICENSE
pyqn-1.4.1.dist-info/METADATA
pyqn-1.4.1.dist-info/WHEEL
pyqn-1.4.1.dist-info/top_level.txt
pyqn-1.4.1.dist-info/RECORD
