Metadata-Version: 2.1
Name: pyqn
Version: 1.4.1
Summary: A package for managing physical units and quantities
Home-page: https://github.com/xnx/pyqn
Author: Christian Hill
Author-email: xn.hill@gmail.com
Project-URL: Bug Reports, https://github.com/xnx/pyqn/issues
Keywords: chemistry,units,physical quantities,unit conversion
Classifier: Development Status :: 4 - Beta
Classifier: Intended Audience :: Science/Research
Classifier: Topic :: Scientific/Engineering :: Chemistry
Classifier: Topic :: Scientific/Engineering :: Physics
Classifier: License :: OSI Approved :: GNU General Public License v3 (GPLv3)
Classifier: Programming Language :: Python :: 3
Classifier: Programming Language :: Python :: 3.6
Classifier: Programming Language :: Python :: 3.7
Classifier: Programming Language :: Python :: 3.8
Classifier: Programming Language :: Python :: 3.9
Classifier: Programming Language :: Python :: 3.10
Classifier: Programming Language :: Python :: 3.11
Classifier: Programming Language :: Python :: 3.12
Classifier: Programming Language :: Python :: 3 :: Only
Classifier: Operating System :: OS Independent
Requires-Python: >=3.6
License-File: LICENSE
Requires-Dist: pyparsing >=2.3
Requires-Dist: importlib-resources >=1.0 ; python_version < "3.7.0"
Provides-Extra: dev
Requires-Dist: black ; extra == 'dev'
Requires-Dist: pytest-cov ; extra == 'dev'
Requires-Dist: tox ; extra == 'dev'
Requires-Dist: ipython ; extra == 'dev'
